vault_dump_restore/__init__.py
vault_dump_restore/cli.py
vault_dump_restore/dump.py
vault_dump_restore/restore.py
vault_dump_restore-0.5.1.dist-info/LICENSE
vault_dump_restore-0.5.1.dist-info/METADATA
vault_dump_restore-0.5.1.dist-info/WHEEL
vault_dump_restore-0.5.1.dist-info/entry_points.txt
vault_dump_restore-0.5.1.dist-info/top_level.txt
vault_dump_restore-0.5.1.dist-info/RECORD
