Metadata-Version: 2.1
Name: vault-dump-restore
Version: 0.5.1
Summary: Dumps keys from a Hashicorp Vault instance to be able to restore it on another instance
Author: Hugo Cisneiros (Eitch)
Author-email: hugo.cisneiros@gmail.com
License: UNKNOWN
Keywords: hashicorp,vault,keys,secrets,backup,restore
Platform: UNKNOWN
Classifier: Development Status :: 3 - Alpha
Classifier: Programming Language :: Python :: 3.6
Classifier: Programming Language :: Python :: 3.8
Classifier: Programming Language :: Python :: 3 :: Only
Requires-Python: >=3.6, <4
License-File: LICENSE
Requires-Dist: hvac (==0.11.2)
